LICENSE
MANIFEST.in
README.md
setup.py
test.py
appstream/__init__.py
appstream/component.py
appstream/errors.py
appstream/store.py
python_appstream.egg-info/PKG-INFO
python_appstream.egg-info/SOURCES.txt
python_appstream.egg-info/dependency_links.txt
python_appstream.egg-info/not-zip-safe
python_appstream.egg-info/pbr.json
python_appstream.egg-info/top_level.txt