Metadata-Version: 1.1
Name: python-appstream
Version: 0.8
Summary: Parse AppStream files when you don't have libappstream-glib
Home-page: http://github.com/hughsie/python-appstream
Author: Ralph Bean
Author-email: rbean@redhat.com
License: LGPLv2+
Platform: UNKNOWN
Classifier: Development Status :: 5 - Production/Stable
Classifier: License :: OSI Approved :: GNU Lesser General Public License v2 or later (LGPLv2+)
Classifier: Intended Audience :: Developers
Classifier: Programming Language :: Python :: 2
Classifier: Programming Language :: Python :: 3
Classifier: Topic :: Text Processing :: Markup :: XML
